{
  "lineIdentifier": "RLQ307834-20673",
  "lineIdentifierNoPrefix": "RL307834-20673",
  "QuoteId": "RLQ307834",
  "quoteIdNoPrefix": "RL307834",
  "QuoteLineId": 20673,
  "quoteDescription": "90x110mm Metallic Labels",
  "recipeId": 17729,
  "quoteDate": "2025-11-13",
  "customerId": "B-21451",
  "customerName": "Print Station",
  "quantity": 5000,
  "sibling": "1",
  "siblingCount": 1,
  "revision": -1,
  "sizeXmm": "90.0",
  "sizeYmm": "110.0",
  "fileName": "",
  "materialName": "PP Metallic Silver",
  "laminateName": "",
  "finishingName": "MATTE LAMINATE",
  "Print Colour": "White + CMYK",
  "Tool": "D0809(6,3)(0,1)1mm Rectangle",
  "Cores": "76mm",
  "Hand/Machine Applied": "MACHINE APPLIED",
  "Supply": "Rolls",
  "kinds": 1,
  "RollDirection": "RD4",
  "lineDescription": "90x110mm Metallic Labels||Size: 90mm x 110mm||Material: PP Metallic Silver||Print Colour: White + CMYK||Tool: D0809(6,3)(0,1)1mm Rectangle||Provided on 76mm Cores||Finishing: MATTE LAMINATE||MACHINE APPLIED||Supply: Rolls||Qty: 5,000||Reseller discount applied||",
  "deliveryToAddress": "Print Station ||112 Durham Street ||HURSTVILLE NSW 2220",
  "processList": "~20907||Indigo||2^^~20908||Digicon||3^^~20909||SLITTER||4^^~20910||RE-ROLL||5^^~20911||PACK AND DISPATCH||6",
  "profitCentreName": "Rentons Labels"
}