{
  "lineIdentifier": "RLQ307841-20698",
  "lineIdentifierNoPrefix": "RL307841-20698",
  "QuoteId": "RLQ307841",
  "quoteIdNoPrefix": "RL307841",
  "QuoteLineId": 20698,
  "quoteDescription": "Replacement Labels - 74x192mm",
  "recipeId": 17750,
  "quoteDate": "2025-11-17",
  "customerId": "B-21900",
  "customerName": "Highlands Natural",
  "quantity": 504,
  "sibling": "1",
  "siblingCount": 1,
  "revision": -1,
  "sizeXmm": "74.0",
  "sizeYmm": "192.0",
  "fileName": "",
  "materialName": "PP Metallic Silver",
  "laminateName": "",
  "finishingName": "RENTONS PREMIUM",
  "Print Colour": "White + CMYK",
  "Tool": "",
  "Cores": "76mm",
  "Hand/Machine Applied": "MACHINE APPLIED",
  "Supply": "Rolls of 504",
  "kinds": 1,
  "RollDirection": "RD4",
  "lineDescription": "Replacement Labels - 74x192mm||Size: 74mm x 192mm||Material: PP Metallic Silver||Print Colour: White + CMYK||Finishing: RENTONS PREMIUM||Provided on 76mm Cores||Hand/Machine Applied: MACHINE APPLIED||Supply: Rolls of 504||Qty: 504||",
  "deliveryToAddress": "Packaging Professionals ||3 Olympic Place ||Kelso NSW 2795",
  "processList": "~21001||Indigo||2^^~21005||Indigo||2.5^^~21002||SLITTER||4^^~21003||RE-ROLL||5^^~21004||PACK AND DISPATCH||6^^~21006||Digital Cut ||2.9",
  "profitCentreName": "Rentons Labels"
}