{
  "lineIdentifier": "RLQ307766-20441",
  "lineIdentifierNoPrefix": "RL307766-20441",
  "QuoteId": "RLQ307766",
  "quoteIdNoPrefix": "RL307766",
  "QuoteLineId": 20441,
  "quoteDescription": "CLEAR PICKLE LABELS PREPRODUCTION RUN",
  "recipeId": 17494,
  "quoteDate": "2025-10-31",
  "customerId": "22447",
  "customerName": "TorShi - Nilofar Boudewyn",
  "quantity": 10,
  "sibling": "1",
  "siblingCount": 1,
  "revision": -1,
  "sizeXmm": "60.0",
  "sizeYmm": "240.0",
  "fileName": "",
  "materialName": "PP Clear",
  "laminateName": "",
  "finishingName": "GLOSS LAMINATE",
  "Print Colour": "White + CMYK",
  "Tool": "D0836(6,4)(0,1)0.6mm Rectangle",
  "Cores": "76mm",
  "Hand/Machine Applied": "HAND APPLIED",
  "Supply": "Not cut to shape ",
  "kinds": 1,
  "RollDirection": "RD4",
  "lineDescription": "CLEAR PICKLE LABELS PREPRODUCTION RUN||Size: 60mm x 240mm||Material: PP Clear||Print Colour: White + CMYK||Tool: D0836(6,4)(0,1)0.6mm Rectangle||Provided on 76mm Cores||Finishing: GLOSS LAMINATE||HAND APPLIED||Supply: Not cut to shape||Testing 8 versions with and without white ink - two sizes 60x240mm + 60x270mm||",
  "deliveryToAddress": "TorShi - Nilofar Boudewyn ||4 Trouton Street ||Balmain NSW 2041",
  "processList": "~19770||Indigo||2^^~19771||Digicon||3^^~19772||SLITTER||4^^~19773||RE-ROLL||5^^~19774||PACK AND DISPATCH||6",
  "profitCentreName": "Rentons Labels"
}