<lineIdentifier>RLQ307770-20451</lineIdentifier>
<lineIdentifierNoPrefix>RL307770-20451</lineIdentifierNoPrefix>
<QuoteId>RLQ307770</QuoteId>
<quoteIdNoPrefix>RL307770</quoteIdNoPrefix>
<QuoteLineId>20451</QuoteLineId>
<quoteDescription>Preventative Health Life Stages Flyers - A5 D/S - 250gsm Gloss</quoteDescription>
<recipeId>17500</recipeId>
<quoteDate>2025-11-03</quoteDate>
<customerId>B-20775</customerId>
<customerName>Brands in Motion</customerName>
<quantity>1000</quantity>
<sibling>2</sibling>
<siblingCount>3</siblingCount>
<revision>-1</revision>
<sizeXmm>210.0</sizeXmm>
<sizeYmm>148.0</sizeYmm>
<fileName/>
<materialName/>
<laminateName/>
<finishingName/>
<Print Colour/>
<Tool/>
<Cores/>
<Hand/Machine Applied/>
<Supply/>
<kinds>1</kinds>
<RollDirection/>
<lineDescription>Preventative Health Life Stages Flyers||Size: A5||Stock: 250gsm Gloss||Print: CMYK both sides||Supply: Flat||Qty: 500 / 1000 / 1500||Reseller discount applied||</lineDescription>
<deliveryToAddress>VetHQ Double Bay ||389 New South Head Road ||Double Bay NSW 2028</deliveryToAddress>
<processList/>
<profitCentreName>Rentons Labels</profitCentreName>