<?xml version="1.0" encoding="UTF-8" ?><jobline><lineIdentifier>Q15040-18264</lineIdentifier><lineIdentifierNoPrefix>15040-18264</lineIdentifierNoPrefix><QuoteId>Q15040</QuoteId><quoteIdNoPrefix>15040</quoteIdNoPrefix><QuoteLineId>18264</QuoteLineId><quoteDescription>RLQ306098 / PA20920</quoteDescription><recipeId>16017</recipeId><quoteDate>2025-07-08</quoteDate><customerId>B-21028</customerId><customerName>Page38</customerName><quantity>15000</quantity><sibling>1</sibling><siblingCount>1</siblingCount><revision>-1</revision><sizeXmm>40.0</sizeXmm><sizeYmm>60.0</sizeYmm><fileName>nan</fileName><materialName>PP Metallic Silver</materialName><laminateName>nan</laminateName><finishingName>MATTE LAMINATE</finishingName><Print_Colour>White + CMYK</Print_Colour><Tool>D0647(6,6)(0,1)2mm Rectangle</Tool><Cores>76mm</Cores><key name="Hand/Machine Applied">HAND APPLIED</key><Supply>Rolls of 1,000 Includes reseller discount *** MATCH COLOUR TO EXISTING LABELS - PANTONE 2955, 4685 &amp; KURZ 429 GOLD *** May need colour adjustment</Supply><kinds>1</kinds><RollDirection>RD2</RollDirection><lineDescription>Size: 40mm x 60mm||Material: PP Metallic Silver||Print Colour: White + CMYK||Tool: D0647(6,6)(0,1)2mm Rectangle||Provided on 76mm Cores||Finishing: MATTE LAMINATE||HAND APPLIED||Supply: Rolls of 1,000 Includes reseller discount *** MATCH COLOUR TO EXISTING LABELS - PANTONE 2955, 4685 KURZ 429 GOLD *** May need colour adjustment||</lineDescription><deliveryToAddress>Page 38 ||38 Australia Avenue ||Matraville NSW 2036</deliveryToAddress><processList><item><barcode>~12276</barcode><name>Indigo</name><sort>2</sort></item><item><barcode>~12277</barcode><name>Digicon</name><sort>3</sort></item><item><barcode>~12278</barcode><name>SLITTER</name><sort>4</sort></item><item><barcode>~12279</barcode><name>RE-ROLL</name><sort>5</sort></item><item><barcode>~12280</barcode><name>PACK AND DISPATCH</name><sort>6</sort></item></processList><profitCentreName>Rentons Labels</profitCentreName></jobline>